README.md
setup.py
erazhan_algorithms/__init__.py
erazhan_algorithms/constants.py
erazhan_algorithms.egg-info/PKG-INFO
erazhan_algorithms.egg-info/SOURCES.txt
erazhan_algorithms.egg-info/dependency_links.txt
erazhan_algorithms.egg-info/requires.txt
erazhan_algorithms.egg-info/top_level.txt
erazhan_algorithms/IntentQA/__init__.py
erazhan_algorithms/IntentQA/data.py
erazhan_algorithms/IntentQA/main_intentqa.py
erazhan_algorithms/IntentQA/models.py
erazhan_algorithms/IntentQA/predict.py
erazhan_algorithms/IntentQA/train.py
erazhan_algorithms/IntentQA/utils.py
erazhan_algorithms/MITC/__init__.py
erazhan_algorithms/MITC/data.py
erazhan_algorithms/MITC/main_mitc.py
erazhan_algorithms/MITC/models.py
erazhan_algorithms/MITC/predict.py
erazhan_algorithms/MITC/train.py
erazhan_algorithms/MITC/utils.py
erazhan_algorithms/NER/__init__.py
erazhan_algorithms/NER/data.py
erazhan_algorithms/NER/main_ner.py
erazhan_algorithms/NER/models.py
erazhan_algorithms/NER/predict.py
erazhan_algorithms/NER/train.py
erazhan_algorithms/NER/utils.py
erazhan_algorithms/QA/__init__.py
erazhan_algorithms/QA/data.py
erazhan_algorithms/QA/main_qa.py
erazhan_algorithms/QA/models.py
erazhan_algorithms/QA/predict.py
erazhan_algorithms/QA/train.py
erazhan_algorithms/QA/utils.py
erazhan_algorithms/TC/__init__.py
erazhan_algorithms/TC/data.py
erazhan_algorithms/TC/main_tc.py
erazhan_algorithms/TC/models.py
erazhan_algorithms/TC/predict.py
erazhan_algorithms/TC/train.py
erazhan_algorithms/TC/utils.py