Metadata-Version: 1.2
Name: erazhan-algorithms
Version: 0.1.2
Summary: algorithm model
Home-page: https://github.com/erazhan/erazhan_algorithms
Author: erazhan
Author-email: erazhan@163.com
License: MIT Licence
Keywords: erazhan_algorithms
Platform: any
Requires-Python: >=3.6.1
